breeze/__init__.py
breeze/__main__.py
breeze/cli.py
breeze/errors.py
breeze/helpers.py
breeze/logger.py
breeze/build/__init__.py
breeze/build/c.py
breeze/build/cpp.py
breeze/utils/__init__.py
breeze/utils/build_utils.py
breeze_build-0.1.4.dist-info/LICENSE
breeze_build-0.1.4.dist-info/METADATA
breeze_build-0.1.4.dist-info/WHEEL
breeze_build-0.1.4.dist-info/entry_points.txt
breeze_build-0.1.4.dist-info/top_level.txt
breeze_build-0.1.4.dist-info/RECORD
